mh_en_exec/__init__.py
mh_en_exec/main.py
mh_en_exec/connection/__init__.py
mh_en_exec/connection/connection_base.py
mh_en_exec/connection/connection_grpc.py
mh_en_exec/connection/connection_pb2.py
mh_en_exec/connection/connection_pb2_grpc.py
mh_en_exec/nodes/__init__.py
mh_en_exec/nodes/common.py
mh_en_exec/nodes/constants.py
mh_en_exec/nodes/exceptions.py
mh_en_exec/nodes/node_base.py
mh_en_exec/nodes/node_factory.py
mh_en_exec/nodes/node_manager.py
mh_en_exec/nodes/ports.py
mh_en_exec/nodes/views/__init__.py
mh_en_exec/resource/__init__.py
mh_en_exec/resource/resource_manager_grpc.py
mh_en_exec-1.0.5.dist-info/LICENSE
mh_en_exec-1.0.5.dist-info/METADATA
mh_en_exec-1.0.5.dist-info/WHEEL
mh_en_exec-1.0.5.dist-info/top_level.txt
mh_en_exec-1.0.5.dist-info/RECORD
