Metadata-Version: 2.1
Name: mh-en-exec
Version: 1.0.5
Summary: Package for executing machine heads external nodes
Home-page: https://mheads.net/external_nodes
Author: Opus
Author-email: mh@opus.co.jp
License: MIT
Classifier: Development Status :: 3 - Alpha
Classifier: License :: OSI Approved :: MIT License
Classifier: Programming Language :: Python :: 3
Classifier: Operating System :: OS Independent
Requires-Python: >=3.9
License-File: LICENSE
Requires-Dist: grpcio>=1.62.1
Requires-Dist: grpcio-tools>=1.62.1
Requires-Dist: opencv-python>=4.9.0.80
